curvereduce/__init__.py
curvereduce-1.0.0.dist-info/METADATA
curvereduce-1.0.0.dist-info/WHEEL
curvereduce-1.0.0.dist-info/licenses/LICENSE
curvereduce-1.0.0.dist-info/RECORD
