Metadata-Version: 2.1
Name: curvereduce
Version: 1.0.0
Summary: Curve simplification per Ramer-Douglas-Peucker.
Project-URL: Homepage, https://github.com/icooper/curvereduce-py
Project-URL: Issues, https://github.com/icooper/curvereduce-py/issues
Author-email: Ian Cooper <icooper@noreply.github.com>
License: MIT License
Classifier: License :: OSI Approved :: MIT License
Classifier: Operating System :: OS Independent
Classifier: Programming Language :: Python :: 3
Requires-Python: >=3.7
